cods/__init__.py
cods/base/__init__.py
cods/base/cp.py
cods/base/data.py
cods/base/loss.py
cods/base/models.py
cods/base/optim.py
cods/base/tr.py
cods/classif/__init_.py
cods/classif/cp.py
cods/classif/loss.py
cods/classif/metrics.py
cods/classif/models.py
cods/classif/score.py
cods/classif/tr.py
cods/classif/visualization.py
cods/classif/data/__init__.py
cods/classif/data/datasets.py
cods/classif/data/predictions.py
cods/od/__init__.py
cods/od/cp.py
cods/od/evaluate.py
cods/od/loss.py
cods/od/metrics.py
cods/od/optim.py
cods/od/score.py
cods/od/utils.py
cods/od/visualization.py
cods/od/data/__init__.py
cods/od/data/datasets.py
cods/od/data/predictions.py
cods/od/models/__init__.py
cods/od/models/detr.py
cods/od/models/model.py
cods/od/models/utils.py
cods/od/models/yolo.py
cods-0.2.dist-info/METADATA
cods-0.2.dist-info/WHEEL
cods-0.2.dist-info/top_level.txt
cods-0.2.dist-info/RECORD
