Metadata-Version: 2.4
Name: cods
Version: 0.2
Summary: Conformal Object Detection & Segmentation
Author: Luca Mossina
Author-email: Léo Andéol <leo@andeol.eu>
Project-URL: Repository, https://github.com/leoandeol/cods/
Classifier: Programming Language :: Python :: 3
Classifier: License :: OSI Approved :: MIT License
Classifier: Operating System :: OS Independent
Requires-Python: >=3.8
